glow2d/__init__.py
glow2d/_glow2d.py
glow2d/_utils.py
glow2d-4.0.0.dist-info/LICENSE.txt
glow2d-4.0.0.dist-info/METADATA
glow2d-4.0.0.dist-info/WHEEL
glow2d-4.0.0.dist-info/top_level.txt
glow2d-4.0.0.dist-info/RECORD
