Metadata-Version: 2.2
Name: glow2d
Version: 4.0.0
Summary: NCAR GLOW model for 2D observation geometry
Home-page: https://sunipkm.github.io/glow2d
Author: Sunip K. Mukherjee
Keywords: thermosphere,ionosphere
Classifier: Development Status :: 5 - Production/Stable
Classifier: Environment :: Console
Classifier: Intended Audience :: Science/Research
Classifier: Operating System :: OS Independent
Classifier: Programming Language :: Fortran
Classifier: Programming Language :: Python :: 3
Classifier: Topic :: Scientific/Engineering :: Atmospheric Science
Requires-Python: >=3.7
License-File: LICENSE.txt
Requires-Dist: numpy>=1.10
Requires-Dist: geopy
Requires-Dist: haversine
Requires-Dist: scipy>=1.14
Requires-Dist: netcdf4
Requires-Dist: pandas
Requires-Dist: tqdm
Requires-Dist: scipy
Requires-Dist: geomagdata
Requires-Dist: glowpython>=4.0.0
Provides-Extra: tests
Requires-Dist: pytest>=3.9; extra == "tests"
Provides-Extra: lint
Requires-Dist: flake8; extra == "lint"
Requires-Dist: flake8-bugbear; extra == "lint"
Requires-Dist: flake8-builtins; extra == "lint"
Requires-Dist: flake8-blind-except; extra == "lint"
Requires-Dist: mypy; extra == "lint"
Provides-Extra: plot
Requires-Dist: matplotlib; extra == "plot"
Requires-Dist: seaborn; extra == "plot"
